[
    {
        "Instancename": "Test1",
        "stability": "prod",
        "Runningservices":"instace,agent",
        "ismonitoring": true,
        "desciption": "testprod"

    },
    {
        "Instancename": "Test2",
        "stability": "prod",
        "Runningservices":"instace,agent",
        "ismonitoring": true,
        "desciption": "testprod"
    },
    {
        "Instancename": "Test3",
        "stability": "prod",
        "Runningservices":"instace,agent",
        "ismonitoring": true,
        "desciption": "testprod"
    },
    {
        "Instancename": "Test4",
        "stability": "prod",
        "Runningservices":"instace,agent",
        "ismonitoring": true,
        "desciption": "testprod"
    },
    {
        "Instancename": "Test5",
        "stability": "dev",
        "Runningservices":"instace,agent",
        "ismonitoring": true,
        "desciption": "testdev"
    },
    {
        "Instancename": "Test6",
        "stability": "dev",
        "Runningservices":"instace,agent",
        "ismonitoring": true,
        "desciption": "testdev"
    },
    {
        "Instancename": "Test7",
        "stability": "dev",
        "Runningservices":"instace,agent",
        "ismonitoring": false,
        "desciption": "testdev"
    },
    {
        "Instancename": "Test8",
        "stability": "dev",
        "Runningservices":"instace,agent",
        "ismonitoring": false,
        "desciption": "testdev"
    }
]